LICENSE
README.md
setup.py
facebook_friends_list_scraper/__init__.py
facebook_friends_list_scraper.egg-info/PKG-INFO
facebook_friends_list_scraper.egg-info/SOURCES.txt
facebook_friends_list_scraper.egg-info/dependency_links.txt
facebook_friends_list_scraper.egg-info/requires.txt
facebook_friends_list_scraper.egg-info/top_level.txt