Metadata-Version: 2.1
Name: facebook-friends-list-scraper
Version: 1.0.1
Summary: A python library to scrape facebook friendslist.
Home-page: UNKNOWN
Author: DataKund
Author-email: datakund@gmail.com
License: Apache License 2.0
Keywords: facebook fb followers friends python bot_studio automation search scraper scrape friendslist friends
Platform: UNKNOWN
License-File: LICENSE
